{
    "data": {
        "seo": {
            "items": [
                {
                    "title": "Wildmoor Whisky KR - Privacy Policy",
                    "keyWords": "WILDMOOR Dark Moorland 23 Year Old Blended Scotch Whisky, WILDMOOR Rugged Coast 30 Year Old Blended Scotch Whisky, WILDMOOR Black Mountain 40 Year Old Blended Scotch Whisky,  WILDMOOR Waking Forest 23 Year Old Blended Scotch Whisky, WILDMOOR Tropical Coast 30 Year Old Blended Scotch Whisky",
                    "description": "WILDMOOR is a new and epic range of blended Scotch whiskies from William Grant & Sons, inspired by the Scottish wilderness."
                }
            ]
        },
        "privacypolicy": {
            "items": [
                {
                    "detailCollection": {
                        "items": [
                            {
                                "title": "WEB SITE USAGE TERMS & CONDITIONS",
                                "content": {
                                    "json": {
                                        "nodeType": "document",
                                        "data": {},
                                        "content": [
                                            {
                                                "nodeType": "paragraph",
                                                "data": {},
                                                "content": [
                                                    {
                                                        "nodeType": "text",
                                                        "value": "Welcome to www.xxxxx.com. This website is jointly operated by:",
                                                        "marks": [],
                                                        "data": {}
                                                    }
                                                ]
                                            },
                                            {
                                                "nodeType": "paragraph",
                                                "data": {},
                                                "content": [
                                                    {
                                                        "nodeType": "text",
                                                        "value": "i. Chivas Brothers Limited, a company incorporated in Scotland\nwith company number SC268758 and VAT number GB 743052164 and\nhaving its registered office at",
                                                        "marks": [],
                                                        "data": {}
                                                    }
                                                ]
                                            },
                                            {
                                                "nodeType": "paragraph",
                                                "data": {},
                                                "content": [
                                                    {
                                                        "nodeType": "text",
                                                        "value": "Kilmalid, Stirling Road, Dumbarton, Scotland, G82 2SS; andii.\nChivas Brothers International Limited, a company incorporated in\nScotland with company number SC646563",
                                                        "marks": [],
                                                        "data": {}
                                                    }
                                                ]
                                            },
                                            {
                                                "nodeType": "paragraph",
                                                "data": {},
                                                "content": [
                                                    {
                                                        "nodeType": "text",
                                                        "value": "and VAT number GB 743052164 and having its registered office at\nKilmalid, Stirling Road, Dumbarton, Scotland, G82 2SStogether,\n“Chivas Brothers”.",
                                                        "marks": [],
                                                        "data": {}
                                                    }
                                                ]
                                            },
                                            {
                                                "nodeType": "paragraph",
                                                "data": {},
                                                "content": [
                                                    {
                                                        "nodeType": "text",
                                                        "value": "In these Terms & Conditions (the “Terms“) “we” and “us“, means\nChivas Brothers.",
                                                        "marks": [],
                                                        "data": {}
                                                    }
                                                ]
                                            },
                                            {
                                                "nodeType": "paragraph",
                                                "data": {},
                                                "content": [
                                                    {
                                                        "nodeType": "text",
                                                        "value": "These Terms apply to the use of the www.xxxxx.com website and all\nrelated sites operated by Chivas Brothers including but not only\nthe home page, micro-sites, splash",
                                                        "marks": [],
                                                        "data": {}
                                                    }
                                                ]
                                            },
                                            {
                                                "nodeType": "paragraph",
                                                "data": {},
                                                "content": [
                                                    {
                                                        "nodeType": "text",
                                                        "value": "page, and all other pages under the same top-level domain name,\nand all content on those pages or sites (the “Site“).",
                                                        "marks": [],
                                                        "data": {}
                                                    }
                                                ]
                                            },
                                            {
                                                "nodeType": "paragraph",
                                                "data": {},
                                                "content": [
                                                    {
                                                        "nodeType": "text",
                                                        "value": "Any reference to “you” or “users” means any person who accesses\nany part of the Site.",
                                                        "marks": [],
                                                        "data": {}
                                                    }
                                                ]
                                            }
                                        ]
                                    },
                                    "links": {
                                        "entries": {
                                            "inline": []
                                        }
                                    }
                                }
                            },
                            {
                                "title": "USE OF THE SITE",
                                "content": {
                                    "json": {
                                        "data": {},
                                        "content": [
                                            {
                                                "data": {},
                                                "content": [
                                                    {
                                                        "data": {},
                                                        "marks": [],
                                                        "value": "Welcome to www.xxxxx.com. This website is jointly operated by:",
                                                        "nodeType": "text"
                                                    }
                                                ],
                                                "nodeType": "paragraph"
                                            },
                                            {
                                                "data": {},
                                                "content": [
                                                    {
                                                        "data": {},
                                                        "marks": [],
                                                        "value": "i. Chivas Brothers Limited, a company incorporated in Scotland with company number SC268758 and VAT number GB 743052164 and having its registered office at",
                                                        "nodeType": "text"
                                                    }
                                                ],
                                                "nodeType": "paragraph"
                                            },
                                            {
                                                "data": {},
                                                "content": [
                                                    {
                                                        "data": {},
                                                        "marks": [],
                                                        "value": "Kilmalid, Stirling Road, Dumbarton, Scotland, G82 2SS; andii. Chivas Brothers International Limited, a company incorporated in Scotland with company number SC646563",
                                                        "nodeType": "text"
                                                    }
                                                ],
                                                "nodeType": "paragraph"
                                            },
                                            {
                                                "data": {},
                                                "content": [
                                                    {
                                                        "data": {},
                                                        "marks": [],
                                                        "value": "and VAT number GB 743052164 and having its registered office at Kilmalid, Stirling Road, Dumbarton, Scotland, G82 2SStogether, “Chivas Brothers”.",
                                                        "nodeType": "text"
                                                    }
                                                ],
                                                "nodeType": "paragraph"
                                            },
                                            {
                                                "data": {},
                                                "content": [
                                                    {
                                                        "data": {},
                                                        "marks": [],
                                                        "value": "In these Terms & Conditions (the “Terms“) “we” and “us“, means Chivas Brothers.",
                                                        "nodeType": "text"
                                                    }
                                                ],
                                                "nodeType": "paragraph"
                                            },
                                            {
                                                "data": {},
                                                "content": [
                                                    {
                                                        "data": {},
                                                        "marks": [],
                                                        "value": "These Terms apply to the use of the www.xxxxx.com website and all related sites operated by Chivas Brothers including but not only the home page, micro-sites, splash",
                                                        "nodeType": "text"
                                                    }
                                                ],
                                                "nodeType": "paragraph"
                                            },
                                            {
                                                "data": {},
                                                "content": [
                                                    {
                                                        "data": {},
                                                        "marks": [],
                                                        "value": "page, and all other pages under the same top-level domain name, and all content on those pages or sites (the “Site“).",
                                                        "nodeType": "text"
                                                    }
                                                ],
                                                "nodeType": "paragraph"
                                            },
                                            {
                                                "data": {},
                                                "content": [
                                                    {
                                                        "data": {},
                                                        "marks": [],
                                                        "value": "Any reference to “you” or “users” means any person who accesses any part of the Site.",
                                                        "nodeType": "text"
                                                    }
                                                ],
                                                "nodeType": "paragraph"
                                            }
                                        ],
                                        "nodeType": "document"
                                    },
                                    "links": {
                                        "entries": {
                                            "inline": []
                                        }
                                    }
                                }
                            },
                            {
                                "title": "LEGAL DRINKING AGE",
                                "content": {
                                    "json": {
                                        "data": {},
                                        "content": [
                                            {
                                                "data": {},
                                                "content": [
                                                    {
                                                        "data": {},
                                                        "marks": [],
                                                        "value": "Welcome to www.xxxxx.com. This website is jointly operated by:",
                                                        "nodeType": "text"
                                                    }
                                                ],
                                                "nodeType": "paragraph"
                                            },
                                            {
                                                "data": {},
                                                "content": [
                                                    {
                                                        "data": {},
                                                        "marks": [],
                                                        "value": "i. Chivas Brothers Limited, a company incorporated in Scotland with company number SC268758 and VAT number GB 743052164 and having its registered office at",
                                                        "nodeType": "text"
                                                    }
                                                ],
                                                "nodeType": "paragraph"
                                            },
                                            {
                                                "data": {},
                                                "content": [
                                                    {
                                                        "data": {},
                                                        "marks": [],
                                                        "value": "Kilmalid, Stirling Road, Dumbarton, Scotland, G82 2SS; andii. Chivas Brothers International Limited, a company incorporated in Scotland with company number SC646563",
                                                        "nodeType": "text"
                                                    }
                                                ],
                                                "nodeType": "paragraph"
                                            },
                                            {
                                                "data": {},
                                                "content": [
                                                    {
                                                        "data": {},
                                                        "marks": [],
                                                        "value": "and VAT number GB 743052164 and having its registered office at Kilmalid, Stirling Road, Dumbarton, Scotland, G82 2SStogether, “Chivas Brothers”.",
                                                        "nodeType": "text"
                                                    }
                                                ],
                                                "nodeType": "paragraph"
                                            },
                                            {
                                                "data": {},
                                                "content": [
                                                    {
                                                        "data": {},
                                                        "marks": [],
                                                        "value": "In these Terms & Conditions (the “Terms“) “we” and “us“, means Chivas Brothers.",
                                                        "nodeType": "text"
                                                    }
                                                ],
                                                "nodeType": "paragraph"
                                            },
                                            {
                                                "data": {},
                                                "content": [
                                                    {
                                                        "data": {},
                                                        "marks": [],
                                                        "value": "These Terms apply to the use of the www.xxxxx.com website and all related sites operated by Chivas Brothers including but not only the home page, micro-sites, splash",
                                                        "nodeType": "text"
                                                    }
                                                ],
                                                "nodeType": "paragraph"
                                            },
                                            {
                                                "data": {},
                                                "content": [
                                                    {
                                                        "data": {},
                                                        "marks": [],
                                                        "value": "page, and all other pages under the same top-level domain name, and all content on those pages or sites (the “Site“).",
                                                        "nodeType": "text"
                                                    }
                                                ],
                                                "nodeType": "paragraph"
                                            },
                                            {
                                                "data": {},
                                                "content": [
                                                    {
                                                        "data": {},
                                                        "marks": [],
                                                        "value": "Any reference to “you” or “users” means any person who accesses any part of the Site.",
                                                        "nodeType": "text"
                                                    }
                                                ],
                                                "nodeType": "paragraph"
                                            }
                                        ],
                                        "nodeType": "document"
                                    },
                                    "links": {
                                        "entries": {
                                            "inline": []
                                        }
                                    }
                                }
                            }
                        ]
                    }
                }
            ]
        }
    }
}